raz_client/__init__.py
raz_client/configure_raz_client.py
raz_client/raz_constants.py
raz_client/raz_signer.py
raz_client/raz_util.py
raz_client/signer_protos_pb2.py
raz_client/examples/__init__.py
raz_client/examples/bucket_location.py
raz_client/examples/delegation_token_example.py
raz_client/examples/file_api.py
raz_client/examples/load_configuration.py
raz_client/examples/multipart_uploads.py
raz_client/examples/ssl_usage_example.py
raz_client-1.1.0.dist-info/LICENSE.txt
raz_client-1.1.0.dist-info/METADATA
raz_client-1.1.0.dist-info/WHEEL
raz_client-1.1.0.dist-info/top_level.txt
raz_client-1.1.0.dist-info/RECORD
