Metadata-Version: 2.1
Name: raz_client
Version: 1.1.0
Summary: boto3 plugin for S3 Ranger authorization
Home-page: https://www.cloudera.com/
Author: Cloudera, Inc.
License: Cloudera Standard License
Keywords: raz boto3
Classifier: Development Status :: 4 - Beta
Classifier: Intended Audience :: End Users/Desktop
Classifier: License :: Other/Proprietary License
Classifier: Natural Language :: English
Classifier: Programming Language :: Python :: 3 :: Only
Classifier: Programming Language :: Python :: 3.6
Classifier: Programming Language :: Python :: 3.7
Classifier: Programming Language :: Python :: 3.8
Classifier: Programming Language :: Python :: 3.9
Requires-Python: >=3
License-File: LICENSE.txt
Requires-Dist: requests >=2.25.1
Requires-Dist: requests-kerberos >=0.14.0
Requires-Dist: protobuf ==4.25.3
Requires-Dist: boto3 >=1.23.10
